{
    "name": "ha-poltava-poweroff",
    "build": {
        "dockerfile": "Dockerfile",
        "context": "."
    },
    "features": {
        "ghcr.io/devcontainers/features/git:1": {},
        "ghcr.io/devcontainers/features/docker-outside-of-docker:1": {}
    },
    "hostRequirements": {
        "cpus": 4,
        "memory": "8gb",
        "storage": "20gb"
    },
    "forwardPorts": [8123],
    "postCreateCommand": "scripts/setup",
    "postStartCommand": "cd /workspaces/ha-poltava-poweroff && nohup bash scripts/devcontainer_ha_guard.sh >/tmp/ha-guard.log 2>&1 &",
    "portsAttributes": {
        "8123": {
            "label": "Home Assistant",
            "onAutoForward": "notify"
        }
    },
    "containerEnv": {
        "PYTHONASYNCIODEBUG": "1"
    },
    "customizations": {
        "vscode": {
            "extensions": [
                "ms-python.vscode-pylance",
                "ms-python.python",
                "ms-azuretools.vscode-docker",
                "charliermarsh.ruff",
                "github.vscode-pull-request-github",
                "ryanluker.vscode-coverage-gutters",
                "tamasfe.even-better-toml",
                "GitHub.copilot"
            ],
            "settings": {
                "python.defaultInterpreterPath": "/usr/local/bin/python",
                "python.pythonPath": "/usr/local/bin/python",
                "[python]": {
                    "editor.defaultFormatter": "charliermarsh.ruff"
                }
            }
        },
        "codespaces": {
            "extensions": [
                "github.copilot",
                "ms-python.python"
            ]
        }
    },
    "remoteUser": "vscode"
}
